solas/__init__.py
solas/_version.py
solas/_config/__init__.py
solas/_config/config.py
solas/action/__init__.py
solas/action/column_group.py
solas/action/correlation.py
solas/action/custom.py
solas/action/default.py
solas/action/enhance.py
solas/action/filter.py
solas/action/generalize.py
solas/action/implicit_tab.py
solas/action/row_group.py
solas/action/temporal.py
solas/action/univariate.py
solas/core/__init__.py
solas/core/frame.py
solas/core/groupby.py
solas/core/loc.py
solas/core/series.py
solas/core/sqltable.py
solas/executor/Executor.py
solas/executor/PandasExecutor.py
solas/executor/SQLExecutor.py
solas/executor/__init__.py
solas/history/__init__.py
solas/history/event.py
solas/history/history.py
solas/implicit/__init__.py
solas/implicit/cg_plotter.py
solas/implicit/implicit_plotter.py
solas/implicit/utils.py
solas/interestingness/__init__.py
solas/interestingness/interestingness.py
solas/interestingness/similarity.py
solas/processor/Compiler.py
solas/processor/Parser.py
solas/processor/Validator.py
solas/processor/__init__.py
solas/utils/__init__.py
solas/utils/date_utils.py
solas/utils/defaults.py
solas/utils/message.py
solas/utils/utils.py
solas/vis/Clause.py
solas/vis/CustomVis.py
solas/vis/Vis.py
solas/vis/VisList.py
solas/vis/__init__.py
solas/vislib/__init__.py
solas/vislib/altair/AltairChart.py
solas/vislib/altair/AltairRenderer.py
solas/vislib/altair/BarChart.py
solas/vislib/altair/BoxPlot.py
solas/vislib/altair/Choropleth.py
solas/vislib/altair/Heatmap.py
solas/vislib/altair/Histogram.py
solas/vislib/altair/LineChart.py
solas/vislib/altair/ScatterChart.py
solas/vislib/altair/__init__.py
solas/vislib/matplotlib/BarChart.py
solas/vislib/matplotlib/Heatmap.py
solas/vislib/matplotlib/Histogram.py
solas/vislib/matplotlib/LineChart.py
solas/vislib/matplotlib/MatplotlibChart.py
solas/vislib/matplotlib/MatplotlibRenderer.py
solas/vislib/matplotlib/ScatterChart.py
solas/vislib/matplotlib/__init__.py
tests/__init__.py
tests/conftest.py
tests/context.py
solas-0.3.0.dist-info/LICENSE
solas-0.3.0.dist-info/METADATA
solas-0.3.0.dist-info/WHEEL
solas-0.3.0.dist-info/top_level.txt
solas-0.3.0.dist-info/RECORD
